pfb/__init__.py
pfb/stimela_cabs.yaml
pfb/deconv/__init__.py
pfb/deconv/clark.py
pfb/deconv/clean.py
pfb/deconv/hogbom.py
pfb/deconv/nnls.py
pfb/deconv/sara.py
pfb/deconv/spotless.py
pfb/operators/__init__.py
pfb/operators/fft.py
pfb/operators/gauss.py
pfb/operators/gridder.py
pfb/operators/hessian.py
pfb/operators/mask.py
pfb/operators/psf.py
pfb/operators/psi.py
pfb/opt/__init__.py
pfb/opt/fista.py
pfb/opt/pcg.py
pfb/opt/power_method.py
pfb/opt/primal_dual.py
pfb/parser/__init__.py
pfb/parser/backward.yaml
pfb/parser/cgopts.yml
pfb/parser/clean.yaml
pfb/parser/degrid.yaml
pfb/parser/dist.yml
pfb/parser/forward.yaml
pfb/parser/fwdbwd.yaml
pfb/parser/grid.yaml
pfb/parser/gridding.yml
pfb/parser/init.yaml
pfb/parser/model2comps.yaml
pfb/parser/pdopts.yml
pfb/parser/pmopts.yml
pfb/parser/restore.yaml
pfb/parser/schemas.py
pfb/parser/spotless.yaml
pfb/prox/__init__.py
pfb/prox/prox2.py
pfb/prox/prox_21.py
pfb/prox/prox_21m.py
pfb/utils/__init__.py
pfb/utils/astrometry.py
pfb/utils/beam.py
pfb/utils/correlations.py
pfb/utils/dist.py
pfb/utils/fits.py
pfb/utils/misc.py
pfb/utils/restoration.py
pfb/utils/spi.py
pfb/utils/stokes.py
pfb/utils/weighting.py
pfb/wavelets/__init__.py
pfb/wavelets/coefficients.py
pfb/wavelets/common.py
pfb/wavelets/convolution.py
pfb/wavelets/intrinsics.py
pfb/wavelets/modes.py
pfb/wavelets/wavelets.py
pfb/workers/__init__.py
pfb/workers/backward.py
pfb/workers/clean.py
pfb/workers/degrid.py
pfb/workers/forward.py
pfb/workers/fwdbwd.py
pfb/workers/grid.py
pfb/workers/init.py
pfb/workers/main.py
pfb/workers/model2comps.py
pfb/workers/residual.py
pfb/workers/restore.py
pfb/workers/spotless.py
tests/__init__.py
tests/conftest.py
tests/test_beam.py
tests/test_clean.py
tests/test_convolve2gaussres.py
tests/test_forwardmodel.py
tests/test_fwdbwd.py
tests/test_kron_matvec.py
tests/test_model2comps.py
tests/test_psi_operator.py
tests/test_spotless.py
tests/test_wavelets.py
tests/test_weighting.py
pfb_clean-0.0.1.dist-info/LICENSE
pfb_clean-0.0.1.dist-info/METADATA
pfb_clean-0.0.1.dist-info/WHEEL
pfb_clean-0.0.1.dist-info/entry_points.txt
pfb_clean-0.0.1.dist-info/top_level.txt
pfb_clean-0.0.1.dist-info/RECORD
